kankakee/__init__.py
kankakee/kankakee.cpython-312-darwin.so
kankakee-1.0.4.dist-info/licenses/LICENSE
kankakee-1.0.4.dist-info/METADATA
kankakee-1.0.4.dist-info/WHEEL
kankakee-1.0.4.dist-info/top_level.txt
kankakee-1.0.4.dist-info/RECORD
