Metadata-Version: 2.4
Name: kankakee
Version: 1.0.4
Summary: A python client/server module for onvif-gui
Author: Stephen Rhodes
Author-email: Stephen Rhodes <sr99622@gmail.com>
License-Expression: Apache-2.0
Project-URL: Homepage, https://github.com/sr99622/kankakee
Project-URL: Bug Tracker, https://github.com/sr99622/kankakee/issues
Classifier: Programming Language :: Python :: 3
Classifier: Operating System :: OS Independent
Requires-Python: >=3.10
License-File: LICENSE
Dynamic: author
Dynamic: license-file
Dynamic: requires-python
